dnsconfigurator/__init__.py
dnsconfigurator/__main__.py
dnsconfigurator/dns_config.py
dnsconfigurator/dns_domain.py
dnsconfigurator/dns_provider.py
dnsconfigurator/dns_provider_cloudflare.py
dnsconfigurator/dns_provider_hetzner.py
dnsconfigurator/dns_record.py
dnsconfigurator/logger.py
dnsconfigurator/main.py
dnsconfigurator/validate.py
dnsconfigurator/examples/sample_config.yaml
dnsconfigurator-1.1.0.dist-info/LICENSE
dnsconfigurator-1.1.0.dist-info/METADATA
dnsconfigurator-1.1.0.dist-info/WHEEL
dnsconfigurator-1.1.0.dist-info/entry_points.txt
dnsconfigurator-1.1.0.dist-info/top_level.txt
dnsconfigurator-1.1.0.dist-info/RECORD
