Metadata-Version: 2.1
Name: dnsconfigurator
Version: 1.1.0
Summary: A DNS management tool to mange DNS setup for domains
Author: Kristian Hougaard
Author-email: khougaard@gmail.com
License: MIT
Classifier: Programming Language :: Python :: 3
Classifier: License :: OSI Approved :: MIT License
Classifier: Operating System :: OS Independent
Requires-Python: >=3.8
License-File: LICENSE
Requires-Dist: pyyaml
Requires-Dist: click
Requires-Dist: colorlog
Requires-Dist: cerberus
Requires-Dist: requests
Requires-Dist: tldextract
Provides-Extra: dev
Requires-Dist: black; extra == "dev"
Requires-Dist: build; extra == "dev"
Requires-Dist: flake8; extra == "dev"
Requires-Dist: pytest; extra == "dev"
Requires-Dist: pytest-cov; extra == "dev"
Requires-Dist: twine; extra == "dev"
